README.md
setup.py
deep_serializer/__init__.py
deep_serializer/des.py
deep_serializer/ser.py
deep_serializer.egg-info/PKG-INFO
deep_serializer.egg-info/SOURCES.txt
deep_serializer.egg-info/dependency_links.txt
deep_serializer.egg-info/requires.txt
deep_serializer.egg-info/top_level.txt
deep_serializer/aux/__init__.py
deep_serializer/aux/errors.py
deep_serializer/aux/example.py
deep_serializer/aux/formats/__init__.py
deep_serializer/aux/formats/json.py