Metadata-Version: 2.1
Name: deep-serializer
Version: 0.0.2
Summary: Package for deep serializing and deserializing
Home-page: https://github.com/164747/python-deep-serializer
Author: David Jacquet
Author-email: jacquet.david@gmail.com
License:  MIT License
Platform: any
Classifier: Programming Language :: Python :: 3
Classifier: License :: OSI Approved :: MIT License
Classifier: Operating System :: OS Independent
Requires-Python: >=3.6.0
